{
	"id": "com.conet.widget.ui5calendarlocal.1",
	"version": "1.0.0",
	"name": "UI5 Calendar Local",
	"description": "Demo UI5 Widget Calendar",
	"newInstancePrefix": "Calendar",
	"icon": "",
	"vendor": "Conet",
	"eula": "",
	"license": "",
	"webcomponents": [
		{
			"kind": "main",
			"tag": "com-conet-widget-ui5calendar1",
			"url": "http://localhost:8888/sac_sdk_ui5widget/ui5Widget.js",
			"integrity": "",
			"ignoreIntegrity": true
		}
	],
	"properties": {
		"selectedDate": {
			"type": "string",
			"description": "Datum",
			"default": ""
		},
		"width": {
			"type": "integer",
			"default": 1000
		},
		"height": {
			"type": "integer",
			"default": 600
		}
	},
	"methods": {
		"setWidth": {
			"description": "Sets the width.",
			"parameters": [
				{
					"name": "newWidth",
					"type": "integer",
					"description": "The width value"
				}
			],
			"body": "this.width = newWidth;"
		},
		"setHeight": {
			"description": "Sets the height.",
			"parameters": [
				{
					"name": "newHeight",
					"type": "integer",
					"description": "The height value"
				}
			],
			"body": "this.height = newHeight;"
		}
	},
	"events": {
		
	}
}

 